{
  "number": "INC10473701",
  "status": "normal",
  "state": "resolved",
  "created": "2025-12-04T06:53:35.000Z",
  "updated": "2025-12-04T07:18:01.000Z",
  "closed": null,
  "crn_masks": "[\"crn:v1:bluemix:public:is-sdn:ca-mon::::\"]",
  "locations": "[\"ca-mon\"]",
  "location_source": "crn_masks",
  "service_names": "[\"is-sdn\"]",
  "regions": "[]",
  "tribe": "Network - Overlay",
  "long_description": "map[MESSAGE:{\"level\":\"info\",\"ts\":1764831195.8255854,\"logger\":\"FABCON\",\"caller\":\"grpcserver/server.go:772\",\"msg\":\"apiExit\",\"fabconRequestID\":\"grpcServer.1364698:CreateRemotePort\",\"elapsed\":0.00036692,\"reply\":\"result:&lt;code:RC_INVAL msg:\"VM with same interfaceName or MAC already exists, port id:UUID{11d36571-6158-4777-b49b-d4ecb731a7e0[  eqaXGw     1  ]} ifname: mac:02:08:a4:00:ba:03 (https://github.ibm.com/cloudnet/fabcon/blob/4d78f5bbfa7128559460a862d816dc7ecedabb10/src/manager/handlers/toporeqvalidator/ports.go#L486)\" &gt; \",\"Log_Counter\":17501798} PRIORITY:6 SYSLOG_IDENTIFIER:ibmcloud-fabcon.fabcon-server _BOOT_ID:4fef18cdd354435bb7a49873a166f7e9 app:bm_mon3-qz1-sr3-rk171-s40-sn2-pensando hostname:mon3-qz1-sr3-rk171-s40-sn2 meta:map[hostname:mon3-qz1-sr3-rk171-s40-sn2 log_agent_version:fb-3.0.4-ibm mzone:ca-mon-prod01-zone3 tag:bm_mon3-qz1-sr3-rk171-s40-sn2-pensando] tag:systemd.log]",
  "outage_start": null,
  "outage_end": null,
  "disruption_time": "0",
  "affected_ci_list": "[\"is-sdn\"]",
  "extracted_resources": "[]",
  "severity": "3",
  "short_description": "Observed service-error-vm_with_same_interface_and_mac_exists issue in fabcon",
  "affected_activity": "",
  "assignment_group": "VPC Overlay Operations SDN SRE",
  "assistant_groups": "[]",
  "cie_assignment_group": "",
  "audience": "not_set",
  "close_code": "closed_resolved_by_caller",
  "close_notes": "Closed/Resolved by Caller",
  "contact_type": "manual",
  "current_status_next_steps": "",
  "customer_facing_impact": "",
  "customers_impacted": "",
  "recurring_event": "false",
  "technical_bridge_start": null,
  "parent_incident": "",
  "case_id": "",
  "problem": "",
  "caused_by_change_number": "",
  "caused_by_change": "false",
  "related_change": "",
  "detection_time": null,
  "identification_time": null,
  "mitigation_time": null,
  "was_customer_impacted": "false",
  "impact_adjustment_factor": "100",
  "unit_type": "customer",
  "units_affected": "0",
  "total_units": "0",
  "user_feedback": "",
  "monitoring_incident_number": "vpc:SDN Overlay SRE:vm_with_same_interface_and_mac_exists:ca-mon-prod",
  "monitoring_incident_assign": "",
  "monitoring_situation": "Observed service-error-vm_with_same_interface_and_mac_exists issue in fabcon",
  "monitoring_crn": "",
  "chronology": "",
  "disable_pager": "false",
  "href": "https://pnp-api-oss.cloud.ibm.com/v2/incidents?offset=0&limit=100&search_by_time=updated&start_time=2025-12-04T07:16:40Z&end_time=2025-12-04T07:21:27Z&severity=3&active=both&segment=Infrastructure%20Services",
  "linked_cases": "0",
  "sys_id": "2de0dd2a9369be1447d97a0b6aba10fb",
  "upstream_problem": "",
  "closed_by": "",
  "reopened_by": "",
  "resolved": "2025-12-04T07:16:32.000Z",
  "resolved_by": "TIP.SA",
  "created_by": "TIP.SA",
  "closed_by_user": "",
  "open_alert": "",
  "open_runbook": "{'href': 'https://w3.ibm.com/services/lighthouse/wikis/view/a18a9d34-1b59-405b-b480-c973100f188d/2f54860c-6784-47cb-96f0-171546db34b7'}",
  "impact_targeted_notification_url": "",
  "caller": "TIP.SA",
  "assigned_to": "lekshmi.nair5@ibm.com",
  "cie_assigned_to": "",
  "comment_list": "[{\"comment\": \"Primary PagerDuty Incident(Q04F1U0E3THNRS) has been resolved.   Resolving incident INC10473701\", \"added_by\": \"snowdev@us.ibm.com\", \"added_on\": \"2025-12-04T07:18:01Z\"}, {\"comment\": \"PagerDuty: Q04F1U0E3THNRS/Global_OverlayOperations SRE_Low was resolved by ServiceNow Application\", \"added_by\": \"snowdev@us.ibm.com\", \"added_on\": \"2025-12-04T07:18:01Z\"}, {\"comment\": \"Resolving PagerDuty incident: PDE7708472/Q04F1U0E3THNRS\", \"added_by\": \"system\", \"added_on\": \"2025-12-04T07:18:01Z\"}, {\"comment\": \"Update from Netcool : Alert is cleared by recovery notice from ibm_cloud_logs.\\n\\n{\\n \\\"alert_id\\\": \\\"vpc:SDN Overlay SRE:vm_with_same_interface_and_mac_exists:ca-mon-prod\\\",\\n \\\"closed_by\\\": \\\"netcool\\\",\\n \\\"crn\\\": {\\n  \\\"service_name\\\": \\\"is-sdn\\\"\\n },\\n \\\"customer_impacting\\\": \\\"false\\\",\\n \\\"extras\\\": [\\n  {\\n   \\\"name\\\": \\\"trace_id\\\",\\n   \\\"value\\\": \\\"d4oivqa6irgs73cbium0\\\"\\n  },\\n  {\\n   \\\"name\\\": \\\"trace_epoch_webhook\\\",\\n   \\\"value\\\": \\\"1764831209\\\"\\n  },\\n  {\\n   \\\"name\\\": \\\"requester\\\",\\n   \\\"value\\\": \\\"netcool\\\"\\n  }\\n ],\\n \\\"incident_id\\\": \\\"INC10473701\\\",\\n \\\"journal\\\": [\\n  \\\"Update from Netcool : Alert is cleared by recovery notice from ibm_cloud_logs.\\\"\\n ],\\n \\\"tip_msg_type\\\": \\\"close.request\\\",\\n \\\"source\\\": \\\"ibm_cloud_logs\\\"\\n}\", \"added_by\": \"TIP.SA\", \"added_on\": \"2025-12-04T07:16:32Z\"}, {\"comment\": \"PagerDuty: Q04F1U0E3THNRS/Global_OverlayOperations SRE_Low was acknowledged/assigned to Lekshmi Nair.\", \"added_by\": \"snowdev@us.ibm.com\", \"added_on\": \"2025-12-04T06:53:56Z\"}]",
  "detection_source": "monitoring_tool",
  "tags": "[]",
  "dbprocessed_time": "2025-12-04T00:00:00.000Z",
  "worknotes": "\"[{\\\"comment\\\": \\\"Primary PagerDuty Incident(Q04F1U0E3THNRS) has been resolved.   Resolving incident INC10473701\\\", \\\"added_by\\\": \\\"snowdev@us.ibm.com\\\", \\\"added_on\\\": \\\"2025-12-04T07:18:01Z\\\"}, {\\\"comment\\\": \\\"PagerDuty: Q04F1U0E3THNRS/Global_OverlayOperations SRE_Low was resolved by ServiceNow Application\\\", \\\"added_by\\\": \\\"snowdev@us.ibm.com\\\", \\\"added_on\\\": \\\"2025-12-04T07:18:01Z\\\"}, {\\\"comment\\\": \\\"Resolving PagerDuty incident: PDE7708472/Q04F1U0E3THNRS\\\", \\\"added_by\\\": \\\"system\\\", \\\"added_on\\\": \\\"2025-12-04T07:18:01Z\\\"}, {\\\"comment\\\": \\\"Update from Netcool : Alert is cleared by recovery notice from ibm_cloud_logs.\\\\n\\\\n{\\\\n \\\\\\\"alert_id\\\\\\\": \\\\\\\"vpc:SDN Overlay SRE:vm_with_same_interface_and_mac_exists:ca-mon-prod\\\\\\\",\\\\n \\\\\\\"closed_by\\\\\\\": \\\\\\\"netcool\\\\\\\",\\\\n \\\\\\\"crn\\\\\\\": {\\\\n  \\\\\\\"service_name\\\\\\\": \\\\\\\"is-sdn\\\\\\\"\\\\n },\\\\n \\\\\\\"customer_impacting\\\\\\\": \\\\\\\"false\\\\\\\",\\\\n \\\\\\\"extras\\\\\\\": [\\\\n  {\\\\n   \\\\\\\"name\\\\\\\": \\\\\\\"trace_id\\\\\\\",\\\\n   \\\\\\\"value\\\\\\\": \\\\\\\"d4oivqa6irgs73cbium0\\\\\\\"\\\\n  },\\\\n  {\\\\n   \\\\\\\"name\\\\\\\": \\\\\\\"trace_epoch_webhook\\\\\\\",\\\\n   \\\\\\\"value\\\\\\\": \\\\\\\"1764831209\\\\\\\"\\\\n  },\\\\n  {\\\\n   \\\\\\\"name\\\\\\\": \\\\\\\"requester\\\\\\\",\\\\n   \\\\\\\"value\\\\\\\": \\\\\\\"netcool\\\\\\\"\\\\n  }\\\\n ],\\\\n \\\\\\\"incident_id\\\\\\\": \\\\\\\"INC10473701\\\\\\\",\\\\n \\\\\\\"journal\\\\\\\": [\\\\n  \\\\\\\"Update from Netcool : Alert is cleared by recovery notice from ibm_cloud_logs.\\\\\\\"\\\\n ],\\\\n \\\\\\\"tip_msg_type\\\\\\\": \\\\\\\"close.request\\\\\\\",\\\\n \\\\\\\"source\\\\\\\": \\\\\\\"ibm_cloud_logs\\\\\\\"\\\\n}\\\", \\\"added_by\\\": \\\"TIP.SA\\\", \\\"added_on\\\": \\\"2025-12-04T07:16:32Z\\\"}, {\\\"comment\\\": \\\"PagerDuty: Q04F1U0E3THNRS/Global_OverlayOperations SRE_Low was acknowledged/assigned to Lekshmi Nair.\\\", \\\"added_by\\\": \\\"snowdev@us.ibm.com\\\", \\\"added_on\\\": \\\"2025-12-04T06:53:56Z\\\"}, {\\\"comment\\\": \\\"PagerDuty: Q04F1U0E3THNRS/Global_OverlayOperations SRE_Low was assigned to Lekshmi Nair.\\\", \\\"added_by\\\": \\\"snowdev@us.ibm.com\\\", \\\"added_on\\\": \\\"2025-12-04T06:53:37Z\\\"}, {\\\"comment\\\": \\\"PagerDuty created incident(Q04F1U0E3THNRS)\\\", \\\"added_by\\\": \\\"system\\\", \\\"added_on\\\": \\\"2025-12-04T06:53:36Z\\\"}, {\\\"comment\\\": \\\"crn:v1:bluemix:public:is-sdn:ca-mon::::\\\\n\\\\n\\\\n{\\\\n \\\\\\\"alert_id\\\\\\\": \\\\\\\"vpc:SDN Overlay SRE:vm_with_same_interface_and_mac_exists:ca-mon-prod\\\\\\\",\\\\n \\\\\\\"crn\\\\\\\": {\\\\n  \\\\\\\"version\\\\\\\": \\\\\\\"v1\\\\\\\",\\\\n  \\\\\\\"cname\\\\\\\": \\\\\\\"bluemix\\\\\\\",\\\\n  \\\\\\\"ctype\\\\\\\": \\\\\\\"public\\\\\\\",\\\\n  \\\\\\\"service_name\\\\\\\": \\\\\\\"is-sdn\\\\\\\",\\\\n  \\\\\\\"location\\\\\\\": \\\\\\\"ca-mon\\\\\\\"\\\\n },\\\\n \\\\\\\"customer_impacting\\\\\\\": \\\\\\\"false\\\\\\\",\\\\n \\\\\\\"disable_pager\\\\\\\": \\\\\\\"false\\\\\\\",\\\\n \\\\\\\"extras\\\\\\\": [\\\\n  {\\\\n   \\\\\\\"name\\\\\\\": \\\\\\\"oss-token-service-name\\\\\\\",\\\\n   \\\\\\\"value\\\\\\\": \\\\\\\"ipopstip@us.ibm.com\\\\\\\"\\\\n  },\\\\n  {\\\\n   \\\\\\\"name\\\\\\\": \\\\\\\"trace_id\\\\\\\",\\\\n   \\\\\\\"value\\\\\\\": \\\\\\\"d4oivqa6irgs73cbium0\\\\\\\"\\\\n  },\\\\n  {\\\\n   \\\\\\\"name\\\\\\\": \\\\\\\"sosat-timestamp-webhook\\\\\\\",\\\\n   \\\\\\\"value\\\\\\\": \\\\\\\"2025-12-04T06:53:29Z\\\\\\\"\\\\n  },\\\\n  {\\\\n   \\\\\\\"name\\\\\\\": \\\\\\\"oss-tip-type\\\\\\\",\\\\n   \\\\\\\"value\\\\\\\": \\\\\\\"alert\\\\\\\"\\\\n  },\\\\n  {\\\\n   \\\\\\\"name\\\\\\\": \\\\\\\"trace_epoch_webhook\\\\\\\",\\\\n   \\\\\\\"value\\\\\\\": \\\\\\\"1764831209\\\\\\\"\\\\n  },\\\\n  {\\\\n   \\\\\\\"name\\\\\\\": \\\\\\\"tip_long_description_base64\\\\\\\",\\\\n   \\\\\\\"value\\\\\\\": \\\\\\\"true\\\\\\\"\\\\n  },\\\\n  {\\\\n   \\\\\\\"name\\\\\\\": \\\\\\\"requester\\\\\\\",\\\\n   \\\\\\\"value\\\\\\\": \\\\\\\"netcool\\\\\\\"\\\\n  }\\\\n ],\\\\n \\\\\\\"tip_msg_type\\\\\\\": \\\\\\\"create.request\\\\\\\",\\\\n \\\\\\\"product_ready_compliance\\\\\\\": \\\\\\\"true\\\\\\\",\\\\n \\\\\\\"runbook_toc_enabled\\\\\\\": \\\\\\\"false\\\\\\\",\\\\n \\\\\\\"runbook_url\\\\\\\": \\\\\\\"https://w3.ibm.com/services/lighthouse/wikis/view/a18a9d34-1b59-405b-b480-c973100f188d/2f54860c-6784-47cb-96f0-171546db34b7\\\\\\\",\\\\n \\\\\\\"severity\\\\\\\": 3,\\\\n \\\\\\\"short_description\\\\\\\": \\\\\\\"Observed service-error-vm_with_same_interface_and_mac_exists issue in fabcon\\\\\\\",\\\\n \\\\\\\"long_description\\\\\\\": \\\\\\\"map[MESSAGE:{\\\\\\\\\\\\\\\"level\\\\\\\\\\\\\\\":\\\\\\\\\\\\\\\"info\\\\\\\\\\\\\\\",\\\\\\\\\\\\\\\"ts\\\\\\\\\\\\\\\":1764831195.8255854,\\\\\\\\\\\\\\\"logger\\\\\\\\\\\\\\\":\\\\\\\\\\\\\\\"FABCON\\\\\\\\\\\\\\\",\\\\\\\\\\\\\\\"caller\\\\\\\\\\\\\\\":\\\\\\\\\\\\\\\"grpcserver/server.go:772\\\\\\\\\\\\\\\",\\\\\\\\\\\\\\\"msg\\\\\\\\\\\\\\\":\\\\\\\\\\\\\\\"apiExit\\\\\\\\\\\\\\\",\\\\\\\\\\\\\\\"fabconRequestID\\\\\\\\\\\\\\\":\\\\\\\\\\\\\\\"grpcServer.1364698:CreateRemotePort\\\\\\\\\\\\\\\",\\\\\\\\\\\\\\\"elapsed\\\\\\\\\\\\\\\":0.00036692,\\\\\\\\\\\\\\\"reply\\\\\\\\\\\\\\\":\\\\\\\\\\\\\\\"result:\\\\\\\\u0026lt;code:RC_INVAL msg:\\\\\\\\\\\\\\\"VM with same interfaceName or MAC already exists, port id:UUID{11d36571-6158-4777-b49b-d4ecb731a7e0[  eqaXGw     1  ]} ifname: mac:02:08:a4:00:ba:03 (https://github.ibm.com/cloudnet/fabcon/blob/4d78f5bbfa7128559460a862d816dc7ecedabb10/src/manager/handlers/toporeqvalidator/ports.go#L486)\\\\\\\\\\\\\\\" \\\\\\\\u0026gt; \\\\\\\\\\\\\\\",\\\\\\\\\\\\\\\"Log_Counter\\\\\\\\\\\\\\\":17501798} PRIORITY:6 SYSLOG_IDENTIFIER:ibmcloud-fabcon.fabcon-server _BOOT_ID:4fef18cdd354435bb7a49873a166f7e9 app:bm_mon3-qz1-sr3-rk171-s40-sn2-pensando hostname:mon3-qz1-sr3-rk171-s40-sn2 meta:map[hostname:mon3-qz1-sr3-rk171-s40-sn2 log_agent_version:fb-3.0.4-ibm mzone:ca-mon-prod01-zone3 tag:bm_mon3-qz1-sr3-rk171-s40-sn2-pensando] tag:systemd.log]\\\\\\\",\\\\n \\\\\\\"situation\\\\\\\": \\\\\\\"Observed service-error-vm_with_same_interface_and_mac_exists issue in fabcon\\\\\\\",\\\\n \\\\\\\"source\\\\\\\": \\\\\\\"ibm_cloud_logs\\\\\\\",\\\\n \\\\\\\"timestamp\\\\\\\": \\\\\\\"2025-12-04T06:53:29Z\\\\\\\",\\\\n \\\\\\\"tribe_name\\\\\\\": \\\\\\\"virtual private cloud\\\\\\\"\\\\n}\\\", \\\"added_by\\\": \\\"TIP.SA\\\", \\\"added_on\\\": \\\"2025-12-04T06:53:35Z\\\"}]\"",
  "metrics": "\"[{\\\"href\\\": \\\"https://pnp-api-oss.cloud.ibm.com/v2/incidents/INC10473701/metrics/2de0156a4725b61472e14af3616d43aa\\\", \\\"active\\\": true, \\\"calc_complete\\\": true, \\\"created\\\": \\\"2025-12-04T06:53:35Z\\\", \\\"description\\\": \\\"Record the Incident Status value at time of PDE creation on the PDE table\\\", \\\"incidentid\\\": \\\"INC10473701\\\", \\\"name\\\": \\\"PD Creation Incident Status\\\", \\\"definition\\\": \\\"MTRC0010008\\\", \\\"id\\\": \\\"2de0156a4725b61472e14af3616d43aa\\\", \\\"type\\\": \\\"Script calculation\\\", \\\"value\\\": \\\"Normal\\\"}, {\\\"href\\\": \\\"https://pnp-api-oss.cloud.ibm.com/v2/incidents/INC10473701/metrics/6626d5aefb21b2546ae0f5c87befdc8a\\\", \\\"active\\\": true, \\\"calc_complete\\\": true, \\\"created\\\": \\\"2025-12-04T07:16:36Z\\\", \\\"description\\\": \\\"When an incident goes into state resolved or closed, calculate the duration from open\\\", \\\"duration\\\": 1377, \\\"end\\\": \\\"2025-12-04T07:16:32Z\\\", \\\"field\\\": \\\"incident_state\\\", \\\"incidentid\\\": \\\"INC10473701\\\", \\\"name\\\": \\\"Create to Resolve Duration\\\", \\\"definition\\\": \\\"MTRC00002\\\", \\\"id\\\": \\\"6626d5aefb21b2546ae0f5c87befdc8a\\\", \\\"start\\\": \\\"2025-12-04T06:53:35Z\\\", \\\"type\\\": \\\"Script calculation\\\"}, {\\\"href\\\": \\\"https://pnp-api-oss.cloud.ibm.com/v2/incidents/INC10473701/metrics/73f0956a93e1fa143ebeb91e1dba10cb\\\", \\\"active\\\": true, \\\"created\\\": \\\"2025-12-04T06:54:01Z\\\", \\\"description\\\": \\\"This metric captures the duration of time an incident is assigned to a user for each user assigned during an incident's life-cycle.\\\", \\\"field\\\": \\\"assigned_to\\\", \\\"incidentid\\\": \\\"INC10473701\\\", \\\"name\\\": \\\"Assigned to Duration\\\", \\\"definition\\\": \\\"MTRC0000003\\\", \\\"id\\\": \\\"73f0956a93e1fa143ebeb91e1dba10cb\\\", \\\"start\\\": \\\"2025-12-04T06:53:56Z\\\", \\\"type\\\": \\\"Field value duration\\\", \\\"value\\\": \\\"Lekshmi Nair\\\"}, {\\\"href\\\": \\\"https://pnp-api-oss.cloud.ibm.com/v2/incidents/INC10473701/metrics/a5e055e22b69bad04a32f414d891bf41\\\", \\\"active\\\": true, \\\"calc_complete\\\": true, \\\"created\\\": \\\"2025-12-04T06:53:35Z\\\", \\\"description\\\": \\\"This metric captures the duration of time an incident has a particular state value for all state values applied during an incident's life-cycle.\\\", \\\"duration\\\": 21, \\\"end\\\": \\\"2025-12-04T06:53:56Z\\\", \\\"field\\\": \\\"incident_state\\\", \\\"incidentid\\\": \\\"INC10473701\\\", \\\"name\\\": \\\"Incident State Duration\\\", \\\"definition\\\": \\\"MTRC0000004\\\", \\\"id\\\": \\\"a5e055e22b69bad04a32f414d891bf41\\\", \\\"start\\\": \\\"2025-12-04T06:53:35Z\\\", \\\"type\\\": \\\"Field value duration\\\", \\\"value\\\": \\\"New\\\"}, {\\\"href\\\": \\\"https://pnp-api-oss.cloud.ibm.com/v2/incidents/INC10473701/metrics/bff0956a93e1fa143ebeb91e1dba10cb\\\", \\\"active\\\": true, \\\"calc_complete\\\": true, \\\"created\\\": \\\"2025-12-04T06:54:01Z\\\", \\\"description\\\": \\\"This metric captures the duration of time an incident has a particular state value for all state values applied during an incident's life-cycle.\\\", \\\"duration\\\": 1356, \\\"end\\\": \\\"2025-12-04T07:16:32Z\\\", \\\"field\\\": \\\"incident_state\\\", \\\"incidentid\\\": \\\"INC10473701\\\", \\\"name\\\": \\\"Incident State Duration\\\", \\\"definition\\\": \\\"MTRC0000004\\\", \\\"id\\\": \\\"bff0956a93e1fa143ebeb91e1dba10cb\\\", \\\"start\\\": \\\"2025-12-04T06:53:56Z\\\", \\\"type\\\": \\\"Field value duration\\\", \\\"value\\\": \\\"In Progress\\\"}, {\\\"href\\\": \\\"https://pnp-api-oss.cloud.ibm.com/v2/incidents/INC10473701/metrics/ea26d5aefb21b2546ae0f5c87befdc8a\\\", \\\"active\\\": true, \\\"created\\\": \\\"2025-12-04T07:16:36Z\\\", \\\"description\\\": \\\"This metric captures the duration of time an incident has a particular state value for all state values applied during an incident's life-cycle.\\\", \\\"field\\\": \\\"incident_state\\\", \\\"incidentid\\\": \\\"INC10473701\\\", \\\"name\\\": \\\"Incident State Duration\\\", \\\"definition\\\": \\\"MTRC0000004\\\", \\\"id\\\": \\\"ea26d5aefb21b2546ae0f5c87befdc8a\\\", \\\"start\\\": \\\"2025-12-04T07:16:32Z\\\", \\\"type\\\": \\\"Field value duration\\\", \\\"value\\\": \\\"Resolved\\\"}, {\\\"href\\\": \\\"https://pnp-api-oss.cloud.ibm.com/v2/incidents/INC10473701/metrics/ede055e22b69bad04a32f414d891bf41\\\", \\\"active\\\": true, \\\"calc_complete\\\": true, \\\"created\\\": \\\"2025-12-04T06:53:35Z\\\", \\\"description\\\": \\\"Overly simplified definition of first call resolution.  \\\\r\\\\n\\\\r\\\\nIf the incident is inactive and the update count (sys_mod_count) is zero, create one of these.\\\", \\\"incidentid\\\": \\\"INC10473701\\\", \\\"name\\\": \\\"First Call Resolution\\\", \\\"definition\\\": \\\"MTRC00005\\\", \\\"id\\\": \\\"ede055e22b69bad04a32f414d891bf41\\\", \\\"type\\\": \\\"Script calculation\\\", \\\"value\\\": \\\"false\\\"}, {\\\"href\\\": \\\"https://pnp-api-oss.cloud.ibm.com/v2/incidents/INC10473701/metrics/e5e055e22b69bad04a32f414d891bf42\\\", \\\"active\\\": true, \\\"created\\\": \\\"2025-12-04T06:53:35Z\\\", \\\"description\\\": \\\"This metric captures the duration of time an incident is assigned to an assignment group for each group assigned during an incident's life-cycle.\\\", \\\"field\\\": \\\"assignment_group\\\", \\\"incidentid\\\": \\\"INC10473701\\\", \\\"name\\\": \\\"Assignment Group\\\", \\\"definition\\\": \\\"MTRC00006\\\", \\\"id\\\": \\\"e5e055e22b69bad04a32f414d891bf42\\\", \\\"start\\\": \\\"2025-12-04T06:53:35Z\\\", \\\"type\\\": \\\"Field value duration\\\", \\\"value\\\": \\\"VPC Overlay Operations SDN SRE\\\"}, {\\\"href\\\": \\\"https://pnp-api-oss.cloud.ibm.com/v2/incidents/INC10473701/metrics/25e015e22b69bad04a32f414d891bfc4\\\", \\\"active\\\": true, \\\"created\\\": \\\"2025-12-04T06:53:35Z\\\", \\\"description\\\": \\\"Special case that closes out (ends) other metrics when an the active flag in the incident turns false\\\", \\\"field\\\": \\\"active\\\", \\\"incidentid\\\": \\\"INC10473701\\\", \\\"name\\\": \\\"Open\\\", \\\"definition\\\": \\\"MTRC0000007\\\", \\\"id\\\": \\\"25e015e22b69bad04a32f414d891bfc4\\\", \\\"start\\\": \\\"2025-12-04T06:53:35Z\\\", \\\"type\\\": \\\"Field value duration\\\", \\\"value\\\": \\\"true\\\"}, {\\\"href\\\": \\\"https://pnp-api-oss.cloud.ibm.com/v2/incidents/INC10473701/metrics/61e055e22b69bad04a32f414d891bf43\\\", \\\"active\\\": true, \\\"created\\\": \\\"2025-12-04T06:53:35Z\\\", \\\"description\\\": \\\"This metric captures the time between when the Incident is created and the first time the incident status is Potential CIE.\\\", \\\"field\\\": \\\"u_status\\\", \\\"incidentid\\\": \\\"INC10473701\\\", \\\"name\\\": \\\"Create to Potential CIE\\\", \\\"definition\\\": \\\"MTRC0010003\\\", \\\"id\\\": \\\"61e055e22b69bad04a32f414d891bf43\\\", \\\"start\\\": \\\"2025-12-04T06:53:35Z\\\", \\\"type\\\": \\\"Field value duration\\\", \\\"value\\\": \\\"Normal\\\"}, {\\\"href\\\": \\\"https://pnp-api-oss.cloud.ibm.com/v2/incidents/INC10473701/metrics/a9e055e22b69bad04a32f414d891bf43\\\", \\\"active\\\": true, \\\"calc_complete\\\": true, \\\"created\\\": \\\"2025-12-04T06:53:36Z\\\", \\\"description\\\": \\\"Records the value and duration of the Incident Status field.  \\\", \\\"duration\\\": 1377, \\\"end\\\": \\\"2025-12-04T07:16:32Z\\\", \\\"field\\\": \\\"u_status\\\", \\\"incidentid\\\": \\\"INC10473701\\\", \\\"name\\\": \\\"Incident status changed\\\", \\\"definition\\\": \\\"MTRC0010016\\\", \\\"id\\\": \\\"a9e055e22b69bad04a32f414d891bf43\\\", \\\"start\\\": \\\"2025-12-04T06:53:35Z\\\", \\\"type\\\": \\\"Field value duration\\\", \\\"value\\\": \\\"Normal\\\"}, {\\\"href\\\": \\\"https://pnp-api-oss.cloud.ibm.com/v2/incidents/INC10473701/metrics/e1e055e22b69bad04a32f414d891bf44\\\", \\\"active\\\": true, \\\"created\\\": \\\"2025-12-04T06:53:36Z\\\", \\\"description\\\": \\\"This metric captures the time between when the Incident is created and the first time the incident status is Confirmed CIE.\\\", \\\"field\\\": \\\"u_status\\\", \\\"incidentid\\\": \\\"INC10473701\\\", \\\"name\\\": \\\"Create to Confirmed CIE\\\", \\\"definition\\\": \\\"MTRC0010004\\\", \\\"id\\\": \\\"e1e055e22b69bad04a32f414d891bf44\\\", \\\"start\\\": \\\"2025-12-04T06:53:35Z\\\", \\\"type\\\": \\\"Field value duration\\\", \\\"value\\\": \\\"Normal\\\"}, {\\\"href\\\": \\\"https://pnp-api-oss.cloud.ibm.com/v2/incidents/INC10473701/metrics/284695ea93257ed04c99b5ba6aba10f0\\\", \\\"active\\\": true, \\\"calc_complete\\\": true, \\\"created\\\": \\\"2025-12-04T07:17:00Z\\\", \\\"description\\\": \\\"How to calculate:\\\\r\\\\nSum of all Durations of Incident status changed w/Value=Confirmed CIE existing metric\\\\r\\\\n\\\\r\\\\nDescription:\\\\r\\\\nSearches for the last time the incident was resolved. Excludes any Incident status changed that were made after resolution. Looks at the cCIE flag has been set to True.\\\", \\\"incidentid\\\": \\\"INC10473701\\\", \\\"name\\\": \\\"Time-in-cCIE\\\", \\\"definition\\\": \\\"MTRC0010016\\\", \\\"id\\\": \\\"284695ea93257ed04c99b5ba6aba10f0\\\", \\\"type\\\": \\\"Script calculation\\\", \\\"value\\\": \\\"0\\\"}, {\\\"href\\\": \\\"https://pnp-api-oss.cloud.ibm.com/v2/incidents/INC10473701/metrics/fc4695e247a936104fc04c4a516d43bd\\\", \\\"active\\\": true, \\\"calc_complete\\\": true, \\\"created\\\": \\\"2025-12-04T07:17:01Z\\\", \\\"description\\\": \\\"How to calculate:\\\\r\\\\nIncident Resolved \\\\u2013 Outage End\\\\r\\\\n\\\\r\\\\nDescription:\\\\r\\\\nIncident Resolved; last time the incident was resolved. Using the start time from the metric \\\\\\\"Incident State Duration\\\\\\\" when the value is Resolved. \\\", \\\"incidentid\\\": \\\"INC10473701\\\", \\\"name\\\": \\\"Time-to-Incident-Resolved\\\", \\\"definition\\\": \\\"MTRC0010017\\\", \\\"id\\\": \\\"fc4695e247a936104fc04c4a516d43bd\\\", \\\"type\\\": \\\"Script calculation\\\", \\\"value\\\": \\\"0\\\"}, {\\\"href\\\": \\\"https://pnp-api-oss.cloud.ibm.com/v2/incidents/INC10473701/metrics/2de055e22b69bad04a32f414d891bf44\\\", \\\"active\\\": true, \\\"calc_complete\\\": true, \\\"created\\\": \\\"2025-12-04T06:53:36Z\\\", \\\"description\\\": \\\"Records the value and duration of the Severity(priority) field.  \\\", \\\"duration\\\": 1377, \\\"end\\\": \\\"2025-12-04T07:16:32Z\\\", \\\"field\\\": \\\"priority\\\", \\\"incidentid\\\": \\\"INC10473701\\\", \\\"name\\\": \\\"Severity (Priority) Changed\\\", \\\"definition\\\": \\\"MTRC0010011\\\", \\\"id\\\": \\\"2de055e22b69bad04a32f414d891bf44\\\", \\\"start\\\": \\\"2025-12-04T06:53:35Z\\\", \\\"type\\\": \\\"Field value duration\\\", \\\"value\\\": \\\"Sev - 3\\\"}, {\\\"href\\\": \\\"https://pnp-api-oss.cloud.ibm.com/v2/incidents/INC10473701/metrics/7846192693e9be1447d97a0b6aba10df\\\", \\\"active\\\": true, \\\"calc_complete\\\": true, \\\"created\\\": \\\"2025-12-04T07:17:01Z\\\", \\\"description\\\": \\\"How to calculate:\\\\r\\\\nSum of all Durations of Incident status changed w/Value=Potential CIE existing metric\\\\r\\\\n\\\\r\\\\nDescription:\\\\r\\\\nSearches for the last time the incident was resolved. Excludes any Incident status changed that were made after resolution.  Looks at the pCIE flag has been set to True.\\\", \\\"incidentid\\\": \\\"INC10473701\\\", \\\"name\\\": \\\"Time-in-pCIE\\\", \\\"definition\\\": \\\"MTRC0010014\\\", \\\"id\\\": \\\"7846192693e9be1447d97a0b6aba10df\\\", \\\"type\\\": \\\"Script calculation\\\", \\\"value\\\": \\\"0\\\"}]\"",
  "metadata": {
    "hostnames": [
      "mon3-qz1-sr3-rk171-s40"
    ]
  }
}