{
  "number": "INC10468619",
  "status": "normal",
  "state": "resolved",
  "created": "2025-12-03T11:48:39.000Z",
  "updated": "2025-12-03T12:00:00.000Z",
  "closed": null,
  "crn_masks": "[\"crn:v1:bluemix:public:is-platform-integration:eu-es::::\"]",
  "locations": "[\"eu-es\"]",
  "location_source": "crn_masks",
  "service_names": "[\"is-platform-integration\"]",
  "regions": "[\"eu-es\"]",
  "tribe": "Virtual Private Cloud - Undercloud",
  "long_description": "[MON] Sysdig agent pod is Ready but missing all metrics is Triggered\n\nTIP Runbook URL: https://pages.github.ibm.com/cloudlab/internal-docs/sysdig_agents_not_sending_metrics.html\nTIP Situation: Sysdig agent pod is Ready but missing all metrics\nTIP Short Description: The Sysdig agent pod is Ready on node mad3-qz1-sr1-rk054-s48 in mzone2y7 but it is not exposing any metrics\nTIP Console: toc\nTIP Self Healing: true\nTIP Self Healing Timeout Seconds: 2400\nTIP CRN: crn:v1:::is-platform-integration:eu-es::mzone2y7:sysdig-agent:sysdig-agent-qlrqb\nIPOPS Enabled: False\n\nEvent Generated:\n\nSeverity:         Medium\nMetric:\n    count by (kube_pod_name, kube_node_name, kube_cluster_name, agent_tag_crn_location) (kube_pod_status_ready{kube_pod_name=~\"sysdig-agent.*\", kube_pod_condition=\"true\"} == 1 AND on (kube_node_name) (kube_node_info{agent_tag_cluster_type=~\"genctl.*|rias\", agent_tag_cluster=~\"mzone.*\"} unless on (kube_node_name) label_replace (sysdig_host_up{agent_tag_cluster_type=~\"genctl.*|rias.*\"}, \"kube_node_name\", \"$1\", \"host_hostname\", \"(.+)\"))) > 0 = 1\nSegment:\n    agent_tag_crn_location = 'eu-es' and kube_cluster_name = 'mzone2y7' and kube_node_name = 'mad3-qz1-sr1-rk054-s48' and kube_pod_name = 'sysdig-agent-qlrqb'\n\nTime:             12/03/2025 11:47 AM UTC\nState:            Triggered\nNotification URL: https://eu-es.monitoring.cloud.ibm.com:443/api/oauth/openid/IBM/2c4a1985f9d5c10bd4842d2d3989088e/746d6f25-66a3-4e4d-9433-6520ea9b2143?redirectRoute=%2Fevents%2Fnotifications%2Fl%3A2419200%2F7988568%2Fdetails\n\n------\n\nTriggered by Alert:\n\nType:         Prometheus\nName:         [MON] Sysdig agent pod is Ready but missing all metrics\nDescription:  Sysdig agent pod is Ready on a node but missing all metrics\nTeam:         Monitor Operations\nScope:\n    Everywhere\nAlert When:   count by (kube_pod_name, kube_node_name, kube_cluster_name, agent_tag_crn_location) (kube_pod_status_ready{kube_pod_name=~\"sysdig-agent.*\", kube_pod_condition=\"true\"} == 1 AND on (kube_node_name) (kube_node_info{agent_tag_cluster_type=~\"genctl.*|rias\", agent_tag_cluster=~\"mzone.*\"} unless on (kube_node_name) label_replace (sysdig_host_up{agent_tag_cluster_type=~\"genctl.*|rias.*\"}, \"kube_node_name\", \"$1\", \"host_hostname\", \"(.+)\"))) > 0\nDuration: 15 m\nAlert URL:    https://eu-es.monitoring.cloud.ibm.com:443/api/oauth/openid/IBM/2c4a1985f9d5c10bd4842d2d3989088e/746d6f25-66a3-4e4d-9433-6520ea9b2143?redirectRoute=%2Falerts%2Frules%3FalertId%3D268750",
  "outage_start": null,
  "outage_end": null,
  "disruption_time": "0",
  "affected_ci_list": "[\"is-platform-integration\"]",
  "extracted_resources": "[]",
  "severity": "3",
  "short_description": "The Sysdig agent pod is Ready on node mad3-qz1-sr1-rk054-s48 in mzone2y7 but it is not exposing any metrics",
  "affected_activity": "performance",
  "assignment_group": "is-ng-vpc",
  "assistant_groups": "[]",
  "cie_assignment_group": "",
  "audience": "not_set",
  "close_code": "closed_resolved_by_caller",
  "close_notes": "Closed/Resolved by Caller",
  "contact_type": "manual",
  "current_status_next_steps": "",
  "customer_facing_impact": "",
  "customers_impacted": "",
  "recurring_event": "false",
  "technical_bridge_start": null,
  "parent_incident": "",
  "case_id": "",
  "problem": "",
  "caused_by_change_number": "",
  "caused_by_change": "false",
  "related_change": "",
  "detection_time": null,
  "identification_time": null,
  "mitigation_time": null,
  "was_customer_impacted": "false",
  "impact_adjustment_factor": "100",
  "unit_type": "customer",
  "units_affected": "0",
  "total_units": "0",
  "user_feedback": "",
  "monitoring_incident_number": "sysdig_alert_id_268750_7988568",
  "monitoring_incident_assign": "",
  "monitoring_situation": "Sysdig agent pod is Ready but missing all metrics",
  "monitoring_crn": "",
  "chronology": "",
  "disable_pager": "true",
  "href": "https://pnp-api-oss.cloud.ibm.com/v2/incidents?offset=200&limit=100&search_by_time=updated&start_time=2025-12-03T11:56:07Z&end_time=2025-12-03T12:01:44Z&severity=3&active=both&segment=Infrastructure%20Services",
  "linked_cases": "0",
  "sys_id": "02da8156fb2d3e146ae0f5c87befdc1d",
  "upstream_problem": "",
  "closed_by": "",
  "reopened_by": "",
  "resolved": "2025-12-03T11:59:28.000Z",
  "resolved_by": "TIP.SA",
  "created_by": "TIP.SA",
  "closed_by_user": "",
  "open_alert": "{'href': 'https://eu-es.monitoring.cloud.ibm.com:443/api/oauth/openid/IBM/2c4a1985f9d5c10bd4842d2d3989088e/746d6f25-66a3-4e4d-9433-6520ea9b2143?redirectRoute=/events/notifications/l:604800/7988568/details'}",
  "open_runbook": "{'href': 'https://pages.github.ibm.com/cloudlab/internal-docs/sysdig_agents_not_sending_metrics.html'}",
  "impact_targeted_notification_url": "",
  "caller": "TIP.SA",
  "assigned_to": "andre.gonzaga1@ibm.com",
  "cie_assigned_to": "",
  "comment_list": "[{\"comment\": \"agonzaga@mad3-qz1-sr1-rk060-s06:~$ kubectl get pods -A -o wide | grep mad3-qz1-sr1-rk054-s48 \\r\\ngenctl        acadia-action-agent-ext1-9m8zw                                    2/2     Running     0               12h     11.13.176.183    mad3-qz1-sr1-rk054-s48   <none>           <none>\\r\\ngenctl        acadia-action-agent-ext2-242ks                                    2/2     Running     0               12h     11.13.176.164    mad3-qz1-sr1-rk054-s48   <none>           <none>\\r\\ngenctl        acadia-action-agent-ktz29                                         2/2     Running     0               12h     11.13.176.214    mad3-qz1-sr1-rk054-s48   <none>           <none>\\r\\ngenctl        acadia-agent-m8qtl                                                2/2     Running     0               13h     11.13.176.99     mad3-qz1-sr1-rk054-s48   <none>           <none>\\r\\ngenctl        acadia-image-action-agent-kjlft                                   2/2     Running     0               13h     11.13.176.213    mad3-qz1-sr1-rk054-s48   <none>           <none>\\r\\ngenctl        fluentbit-logs-j6q6p                                              4/4     Running     0               12h     11.13.176.119    mad3-qz1-sr1-rk054-s48   <none>           <none>\\r\\ngenctl        fluentbit-qradar-5vql7                                            4/4     Running     0               12h     11.13.176.155    mad3-qz1-sr1-rk054-s48   <none>           <none>\\r\\ngenctl        grafana-alloy-agent-c8q66                                         3/3     Running     0               11d     10.22.197.141    mad3-qz1-sr1-rk054-s48   <none>           <none>\\r\\ngenctl        ifv-rclone-config-writer-sh5dq                                    1/1     Running     0               14d     11.13.176.8      mad3-qz1-sr1-rk054-s48   <none>           <none>\\r\\ngenctl        storage-agent-krlzg                                               2/2     Running     0               12h     11.13.176.117    mad3-qz1-sr1-rk054-s48   <none>           <none>\\r\\ngenctl        uploadr050-7565b65e-9a9d-4463-8a50-56aa459abbf1-a2916b02cb9g6h8   1/1     Running     0               3h55m   11.13.176.107    mad3-qz1-sr1-rk054-s48   <none>           <none>\\r\\nkube-system   kube-proxy-vq94n                                                  1/1     Running     0               14d     10.22.197.141    mad3-qz1-sr1-rk054-s48   <none>           <none>\\r\\nsysdig        sysdig-agent-qlrqb                                                3/3     Running     0               11d     10.22.197.141    mad3-qz1-sr1-rk054-s48   <none>           <none>\\r\\n\\r\\n\\r\\nChecking logs \\r\\n\\r\\nagonzaga@mad3-qz1-sr1-rk060-s06:~$ kubectl logs sysdig-agent-qlrqb -n sysdig -c sysdig-agent --since 15m | grep \\\"Lost connection (reading header)\\\"\\r\\nagonzaga@mad3-qz1-sr1-rk060-s06:~$ kubectl logs sysdig-agent-qlrqb -n sysdig -c sysdig-agent  | grep \\\"Lost connection (reading header)\\\"\\r\\nagonzaga@mad3-qz1-sr1-rk060-s06:~$\\r\\n\\r\\n\\r\\nDeleting pod\\r\\n\\r\\nagonzaga@mad3-qz1-sr1-rk060-s06:~$ kubectl delete po sysdig-agent-qlrqb -n sysdig \\r\\npod \\\"sysdig-agent-qlrqb\\\" deleted\\r\\n\\r\\n\\r\\nPod running \\r\\nsysdig        sysdig-agent-lrtxm                                                3/3     Running     0               69s     10.22.197.141    mad3-qz1-sr1-rk054-s48   <none>           <none>\", \"added_by\": \"andre.gonzaga1@ibm.com\", \"added_on\": \"2025-12-03T12:00:00Z\"}, {\"comment\": \"Update from Netcool : Alert is cleared by recovery notice from Sysdig Cloud.\\n\\n{\\n \\\"alert_id\\\": \\\"sysdig_alert_id_268750_7988568\\\",\\n \\\"closed_by\\\": \\\"netcool\\\",\\n \\\"crn\\\": {\\n  \\\"service_name\\\": \\\"is-platform-integration\\\"\\n },\\n \\\"customer_impacting\\\": \\\"false\\\",\\n \\\"extras\\\": [\\n  {\\n   \\\"name\\\": \\\"trace_id\\\",\\n   \\\"value\\\": \\\"d4o272ucr2cs739sv8v0\\\"\\n  },\\n  {\\n   \\\"name\\\": \\\"trace_epoch_webhook\\\",\\n   \\\"value\\\": \\\"1764762507\\\"\\n  },\\n  {\\n   \\\"name\\\": \\\"requester\\\",\\n   \\\"value\\\": \\\"netcool\\\"\\n  }\\n ],\\n \\\"incident_id\\\": \\\"INC10468619\\\",\\n \\\"journal\\\": [\\n  \\\"Update from Netcool : Alert is cleared by recovery notice from Sysdig Cloud.\\\"\\n ],\\n \\\"tip_msg_type\\\": \\\"close.request\\\",\\n \\\"source\\\": \\\"Sysdig Cloud\\\"\\n}\", \"added_by\": \"TIP.SA\", \"added_on\": \"2025-12-03T11:59:27Z\"}, {\"comment\": \"Could not find error log Lost connection (reading header) in the pods container *sysdig-agent* logs. Quitting!\", \"added_by\": \"ipops-automation@ibm.com\", \"added_on\": \"2025-12-03T11:52:29Z\"}, {\"comment\": \"Attachment: [code]<a href=\\\"/sys_attachment.do?sys_id=60bb0d5a47e932104fc04c4a516d4348\\\">pod_logs_sysdig-agent-qlrqb-sysdig-agent.log</a>[/code] has been attached  by Ipops-automation\", \"added_by\": \"ipops-automation@ibm.com\", \"added_on\": \"2025-12-03T11:52:23Z\"}, {\"comment\": \"Cloud Service: is-platform-integration \\n Invalid Resource :sysdig-agent-qlrqb\\n crn:v1:bluemix:public:is-platform-integration:eu-es::mzone2y7:sysdig-agent:sysdig-agent-qlrqb\", \"added_by\": \"TIP.SA\", \"added_on\": \"2025-12-03T11:48:39Z\"}]",
  "detection_source": "monitoring_tool",
  "tags": "[]",
  "dbprocessed_time": "2025-12-03T00:00:00.000Z",
  "worknotes": "\"[{\\\"comment\\\": \\\"agonzaga@mad3-qz1-sr1-rk060-s06:~$ kubectl get pods -A -o wide | grep mad3-qz1-sr1-rk054-s48 \\\\r\\\\ngenctl        acadia-action-agent-ext1-9m8zw                                    2/2     Running     0               12h     11.13.176.183    mad3-qz1-sr1-rk054-s48   <none>           <none>\\\\r\\\\ngenctl        acadia-action-agent-ext2-242ks                                    2/2     Running     0               12h     11.13.176.164    mad3-qz1-sr1-rk054-s48   <none>           <none>\\\\r\\\\ngenctl        acadia-action-agent-ktz29                                         2/2     Running     0               12h     11.13.176.214    mad3-qz1-sr1-rk054-s48   <none>           <none>\\\\r\\\\ngenctl        acadia-agent-m8qtl                                                2/2     Running     0               13h     11.13.176.99     mad3-qz1-sr1-rk054-s48   <none>           <none>\\\\r\\\\ngenctl        acadia-image-action-agent-kjlft                                   2/2     Running     0               13h     11.13.176.213    mad3-qz1-sr1-rk054-s48   <none>           <none>\\\\r\\\\ngenctl        fluentbit-logs-j6q6p                                              4/4     Running     0               12h     11.13.176.119    mad3-qz1-sr1-rk054-s48   <none>           <none>\\\\r\\\\ngenctl        fluentbit-qradar-5vql7                                            4/4     Running     0               12h     11.13.176.155    mad3-qz1-sr1-rk054-s48   <none>           <none>\\\\r\\\\ngenctl        grafana-alloy-agent-c8q66                                         3/3     Running     0               11d     10.22.197.141    mad3-qz1-sr1-rk054-s48   <none>           <none>\\\\r\\\\ngenctl        ifv-rclone-config-writer-sh5dq                                    1/1     Running     0               14d     11.13.176.8      mad3-qz1-sr1-rk054-s48   <none>           <none>\\\\r\\\\ngenctl        storage-agent-krlzg                                               2/2     Running     0               12h     11.13.176.117    mad3-qz1-sr1-rk054-s48   <none>           <none>\\\\r\\\\ngenctl        uploadr050-7565b65e-9a9d-4463-8a50-56aa459abbf1-a2916b02cb9g6h8   1/1     Running     0               3h55m   11.13.176.107    mad3-qz1-sr1-rk054-s48   <none>           <none>\\\\r\\\\nkube-system   kube-proxy-vq94n                                                  1/1     Running     0               14d     10.22.197.141    mad3-qz1-sr1-rk054-s48   <none>           <none>\\\\r\\\\nsysdig        sysdig-agent-qlrqb                                                3/3     Running     0               11d     10.22.197.141    mad3-qz1-sr1-rk054-s48   <none>           <none>\\\\r\\\\n\\\\r\\\\n\\\\r\\\\nChecking logs \\\\r\\\\n\\\\r\\\\nagonzaga@mad3-qz1-sr1-rk060-s06:~$ kubectl logs sysdig-agent-qlrqb -n sysdig -c sysdig-agent --since 15m | grep \\\\\\\"Lost connection (reading header)\\\\\\\"\\\\r\\\\nagonzaga@mad3-qz1-sr1-rk060-s06:~$ kubectl logs sysdig-agent-qlrqb -n sysdig -c sysdig-agent  | grep \\\\\\\"Lost connection (reading header)\\\\\\\"\\\\r\\\\nagonzaga@mad3-qz1-sr1-rk060-s06:~$\\\\r\\\\n\\\\r\\\\n\\\\r\\\\nDeleting pod\\\\r\\\\n\\\\r\\\\nagonzaga@mad3-qz1-sr1-rk060-s06:~$ kubectl delete po sysdig-agent-qlrqb -n sysdig \\\\r\\\\npod \\\\\\\"sysdig-agent-qlrqb\\\\\\\" deleted\\\\r\\\\n\\\\r\\\\n\\\\r\\\\nPod running \\\\r\\\\nsysdig        sysdig-agent-lrtxm                                                3/3     Running     0               69s     10.22.197.141    mad3-qz1-sr1-rk054-s48   <none>           <none>\\\", \\\"added_by\\\": \\\"andre.gonzaga1@ibm.com\\\", \\\"added_on\\\": \\\"2025-12-03T12:00:00Z\\\"}, {\\\"comment\\\": \\\"Update from Netcool : Alert is cleared by recovery notice from Sysdig Cloud.\\\\n\\\\n{\\\\n \\\\\\\"alert_id\\\\\\\": \\\\\\\"sysdig_alert_id_268750_7988568\\\\\\\",\\\\n \\\\\\\"closed_by\\\\\\\": \\\\\\\"netcool\\\\\\\",\\\\n \\\\\\\"crn\\\\\\\": {\\\\n  \\\\\\\"service_name\\\\\\\": \\\\\\\"is-platform-integration\\\\\\\"\\\\n },\\\\n \\\\\\\"customer_impacting\\\\\\\": \\\\\\\"false\\\\\\\",\\\\n \\\\\\\"extras\\\\\\\": [\\\\n  {\\\\n   \\\\\\\"name\\\\\\\": \\\\\\\"trace_id\\\\\\\",\\\\n   \\\\\\\"value\\\\\\\": \\\\\\\"d4o272ucr2cs739sv8v0\\\\\\\"\\\\n  },\\\\n  {\\\\n   \\\\\\\"name\\\\\\\": \\\\\\\"trace_epoch_webhook\\\\\\\",\\\\n   \\\\\\\"value\\\\\\\": \\\\\\\"1764762507\\\\\\\"\\\\n  },\\\\n  {\\\\n   \\\\\\\"name\\\\\\\": \\\\\\\"requester\\\\\\\",\\\\n   \\\\\\\"value\\\\\\\": \\\\\\\"netcool\\\\\\\"\\\\n  }\\\\n ],\\\\n \\\\\\\"incident_id\\\\\\\": \\\\\\\"INC10468619\\\\\\\",\\\\n \\\\\\\"journal\\\\\\\": [\\\\n  \\\\\\\"Update from Netcool : Alert is cleared by recovery notice from Sysdig Cloud.\\\\\\\"\\\\n ],\\\\n \\\\\\\"tip_msg_type\\\\\\\": \\\\\\\"close.request\\\\\\\",\\\\n \\\\\\\"source\\\\\\\": \\\\\\\"Sysdig Cloud\\\\\\\"\\\\n}\\\", \\\"added_by\\\": \\\"TIP.SA\\\", \\\"added_on\\\": \\\"2025-12-03T11:59:27Z\\\"}, {\\\"comment\\\": \\\"Could not find error log Lost connection (reading header) in the pods container *sysdig-agent* logs. Quitting!\\\", \\\"added_by\\\": \\\"ipops-automation@ibm.com\\\", \\\"added_on\\\": \\\"2025-12-03T11:52:29Z\\\"}, {\\\"comment\\\": \\\"Attachment: [code]<a href=\\\\\\\"/sys_attachment.do?sys_id=60bb0d5a47e932104fc04c4a516d4348\\\\\\\">pod_logs_sysdig-agent-qlrqb-sysdig-agent.log</a>[/code] has been attached  by Ipops-automation\\\", \\\"added_by\\\": \\\"ipops-automation@ibm.com\\\", \\\"added_on\\\": \\\"2025-12-03T11:52:23Z\\\"}, {\\\"comment\\\": \\\"Cloud Service: is-platform-integration \\\\n Invalid Resource :sysdig-agent-qlrqb\\\\n crn:v1:bluemix:public:is-platform-integration:eu-es::mzone2y7:sysdig-agent:sysdig-agent-qlrqb\\\", \\\"added_by\\\": \\\"TIP.SA\\\", \\\"added_on\\\": \\\"2025-12-03T11:48:39Z\\\"}, {\\\"comment\\\": \\\"crn:v1:bluemix:public:is-platform-integration:eu-es::mzone2y7:sysdig-agent:sysdig-agent-qlrqb\\\\n\\\\nUpdate from Netcool : Self-healing is in-progress.\\\\n\\\\n{\\\\n \\\\\\\"alert_id\\\\\\\": \\\\\\\"sysdig_alert_id_268750_7988568\\\\\\\",\\\\n \\\\\\\"alert_ui_url\\\\\\\": \\\\\\\"https://eu-es.monitoring.cloud.ibm.com:443/api/oauth/openid/IBM/2c4a1985f9d5c10bd4842d2d3989088e/746d6f25-66a3-4e4d-9433-6520ea9b2143?redirectRoute=%2Fevents%2Fnotifications%2Fl%3A604800%2F7988568%2Fdetails\\\\\\\",\\\\n \\\\\\\"crn\\\\\\\": {\\\\n  \\\\\\\"version\\\\\\\": \\\\\\\"v1\\\\\\\",\\\\n  \\\\\\\"cname\\\\\\\": \\\\\\\"bluemix\\\\\\\",\\\\n  \\\\\\\"ctype\\\\\\\": \\\\\\\"public\\\\\\\",\\\\n  \\\\\\\"service_name\\\\\\\": \\\\\\\"is-platform-integration\\\\\\\",\\\\n  \\\\\\\"location\\\\\\\": \\\\\\\"eu-es\\\\\\\",\\\\n  \\\\\\\"service_instance\\\\\\\": \\\\\\\"mzone2y7\\\\\\\",\\\\n  \\\\\\\"resource_type\\\\\\\": \\\\\\\"sysdig-agent\\\\\\\",\\\\n  \\\\\\\"resource\\\\\\\": \\\\\\\"sysdig-agent-qlrqb\\\\\\\"\\\\n },\\\\n \\\\\\\"customer_impacting\\\\\\\": \\\\\\\"false\\\\\\\",\\\\n \\\\\\\"disable_pager\\\\\\\": \\\\\\\"true\\\\\\\",\\\\n \\\\\\\"extras\\\\\\\": [\\\\n  {\\\\n   \\\\\\\"name\\\\\\\": \\\\\\\"oss-token-service-name\\\\\\\",\\\\n   \\\\\\\"value\\\\\\\": \\\\\\\"iam-ServiceId-bc9c4043-1e48-4092-9baa-75ca02944aaa\\\\\\\"\\\\n  },\\\\n  {\\\\n   \\\\\\\"name\\\\\\\": \\\\\\\"trace_id\\\\\\\",\\\\n   \\\\\\\"value\\\\\\\": \\\\\\\"d4o272ucr2cs739sv8v0\\\\\\\"\\\\n  },\\\\n  {\\\\n   \\\\\\\"name\\\\\\\": \\\\\\\"sosat-timestamp-webhook\\\\\\\",\\\\n   \\\\\\\"value\\\\\\\": \\\\\\\"2025-12-03T11:48:27Z\\\\\\\"\\\\n  },\\\\n  {\\\\n   \\\\\\\"name\\\\\\\": \\\\\\\"oss-tip-type\\\\\\\",\\\\n   \\\\\\\"value\\\\\\\": \\\\\\\"alert\\\\\\\"\\\\n  },\\\\n  {\\\\n   \\\\\\\"name\\\\\\\": \\\\\\\"trace_epoch_webhook\\\\\\\",\\\\n   \\\\\\\"value\\\\\\\": \\\\\\\"1764762507\\\\\\\"\\\\n  },\\\\n  {\\\\n   \\\\\\\"name\\\\\\\": \\\\\\\"tip_long_description_base64\\\\\\\",\\\\n   \\\\\\\"value\\\\\\\": \\\\\\\"true\\\\\\\"\\\\n  },\\\\n  {\\\\n   \\\\\\\"name\\\\\\\": \\\\\\\"requester\\\\\\\",\\\\n   \\\\\\\"value\\\\\\\": \\\\\\\"netcool\\\\\\\"\\\\n  }\\\\n ],\\\\n \\\\\\\"journal\\\\\\\": [\\\\n  \\\\\\\"\\\\\\\\nUpdate from Netcool : Self-healing is in-progress.\\\\\\\"\\\\n ],\\\\n \\\\\\\"tip_msg_type\\\\\\\": \\\\\\\"create.request\\\\\\\",\\\\n \\\\\\\"product_ready_compliance\\\\\\\": \\\\\\\"true\\\\\\\",\\\\n \\\\\\\"runbook_toc_enabled\\\\\\\": \\\\\\\"false\\\\\\\",\\\\n \\\\\\\"runbook_url\\\\\\\": \\\\\\\"https://pages.github.ibm.com/cloudlab/internal-docs/sysdig_agents_not_sending_metrics.html\\\\\\\",\\\\n \\\\\\\"severity\\\\\\\": 3,\\\\n \\\\\\\"short_description\\\\\\\": \\\\\\\"The Sysdig agent pod is Ready on node mad3-qz1-sr1-rk054-s48 in mzone2y7 but it is not exposing any metrics\\\\\\\",\\\\n \\\\\\\"long_description\\\\\\\": \\\\\\\"[MON] Sysdig agent pod is Ready but missing all metrics is Triggered\\\\\\\\n\\\\\\\\nTIP Runbook URL: https://pages.github.ibm.com/cloudlab/internal-docs/sysdig_agents_not_sending_metrics.html\\\\\\\\nTIP Situation: Sysdig agent pod is Ready but missing all metrics\\\\\\\\nTIP Short Description: The Sysdig agent pod is Ready on node mad3-qz1-sr1-rk054-s48 in mzone2y7 but it is not exposing any metrics\\\\\\\\nTIP Console: toc\\\\\\\\nTIP Self Healing: true\\\\\\\\nTIP Self Healing Timeout Seconds: 2400\\\\\\\\nTIP CRN: crn:v1:::is-platform-integration:eu-es::mzone2y7:sysdig-agent:sysdig-agent-qlrqb\\\\\\\\nIPOPS Enabled: False\\\\\\\\n\\\\\\\\nEvent Generated:\\\\\\\\n\\\\\\\\nSeverity:         Medium\\\\\\\\nMetric:\\\\\\\\n    count by (kube_pod_name, kube_node_name, kube_cluster_name, agent_tag_crn_location) (kube_pod_status_ready{kube_pod_name=~\\\\\\\\\\\\\\\"sysdig-agent.*\\\\\\\\\\\\\\\", kube_pod_condition=\\\\\\\\\\\\\\\"true\\\\\\\\\\\\\\\"} == 1 AND on (kube_node_name) (kube_node_info{agent_tag_cluster_type=~\\\\\\\\\\\\\\\"genctl.*|rias\\\\\\\\\\\\\\\", agent_tag_cluster=~\\\\\\\\\\\\\\\"mzone.*\\\\\\\\\\\\\\\"} unless on (kube_node_name) label_replace (sysdig_host_up{agent_tag_cluster_type=~\\\\\\\\\\\\\\\"genctl.*|rias.*\\\\\\\\\\\\\\\"}, \\\\\\\\\\\\\\\"kube_node_name\\\\\\\\\\\\\\\", \\\\\\\\\\\\\\\"$1\\\\\\\\\\\\\\\", \\\\\\\\\\\\\\\"host_hostname\\\\\\\\\\\\\\\", \\\\\\\\\\\\\\\"(.+)\\\\\\\\\\\\\\\"))) \\\\\\\\u003e 0 = 1\\\\\\\\nSegment:\\\\\\\\n    agent_tag_crn_location = 'eu-es' and kube_cluster_name = 'mzone2y7' and kube_node_name = 'mad3-qz1-sr1-rk054-s48' and kube_pod_name = 'sysdig-agent-qlrqb'\\\\\\\\n\\\\\\\\nTime:             12/03/2025 11:47 AM UTC\\\\\\\\nState:            Triggered\\\\\\\\nNotification URL: https://eu-es.monitoring.cloud.ibm.com:443/api/oauth/openid/IBM/2c4a1985f9d5c10bd4842d2d3989088e/746d6f25-66a3-4e4d-9433-6520ea9b2143?redirectRoute=%2Fevents%2Fnotifications%2Fl%3A2419200%2F7988568%2Fdetails\\\\\\\\n\\\\\\\\n------\\\\\\\\n\\\\\\\\nTriggered by Alert:\\\\\\\\n\\\\\\\\nType:         Prometheus\\\\\\\\nName:         [MON] Sysdig agent pod is Ready but missing all metrics\\\\\\\\nDescription:  Sysdig agent pod is Ready on a node but missing all metrics\\\\\\\\nTeam:         Monitor Operations\\\\\\\\nScope:\\\\\\\\n    Everywhere\\\\\\\\nAlert When:   count by (kube_pod_name, kube_node_name, kube_cluster_name, agent_tag_crn_location) (kube_pod_status_ready{kube_pod_name=~\\\\\\\\\\\\\\\"sysdig-agent.*\\\\\\\\\\\\\\\", kube_pod_condition=\\\\\\\\\\\\\\\"true\\\\\\\\\\\\\\\"} == 1 AND on (kube_node_name) (kube_node_info{agent_tag_cluster_type=~\\\\\\\\\\\\\\\"genctl.*|rias\\\\\\\\\\\\\\\", agent_tag_cluster=~\\\\\\\\\\\\\\\"mzone.*\\\\\\\\\\\\\\\"} unless on (kube_node_name) label_replace (sysdig_host_up{agent_tag_cluster_type=~\\\\\\\\\\\\\\\"genctl.*|rias.*\\\\\\\\\\\\\\\"}, \\\\\\\\\\\\\\\"kube_node_name\\\\\\\\\\\\\\\", \\\\\\\\\\\\\\\"$1\\\\\\\\\\\\\\\", \\\\\\\\\\\\\\\"host_hostname\\\\\\\\\\\\\\\", \\\\\\\\\\\\\\\"(.+)\\\\\\\\\\\\\\\"))) \\\\\\\\u003e 0\\\\\\\\nDuration: 15 m\\\\\\\\nAlert URL:    https://eu-es.monitoring.cloud.ibm.com:443/api/oauth/openid/IBM/2c4a1985f9d5c10bd4842d2d3989088e/746d6f25-66a3-4e4d-9433-6520ea9b2143?redirectRoute=%2Falerts%2Frules%3FalertId%3D268750\\\\\\\",\\\\n \\\\\\\"situation\\\\\\\": \\\\\\\"Sysdig agent pod is Ready but missing all metrics\\\\\\\",\\\\n \\\\\\\"source\\\\\\\": \\\\\\\"Sysdig Cloud\\\\\\\",\\\\n \\\\\\\"timestamp\\\\\\\": \\\\\\\"2025-12-03T11:48:27Z\\\\\\\",\\\\n \\\\\\\"tribe_name\\\\\\\": \\\\\\\"Virtual Private Cloud\\\\\\\"\\\\n}\\\", \\\"added_by\\\": \\\"TIP.SA\\\", \\\"added_on\\\": \\\"2025-12-03T11:48:39Z\\\"}]\"",
  "metrics": "\"[{\\\"href\\\": \\\"https://pnp-api-oss.cloud.ibm.com/v2/incidents/INC10468619/metrics/815d495693a9b214fce8b3f17cba106d\\\", \\\"active\\\": true, \\\"calc_complete\\\": true, \\\"created\\\": \\\"2025-12-03T11:59:30Z\\\", \\\"description\\\": \\\"When an incident goes into state resolved or closed, calculate the duration from open\\\", \\\"duration\\\": 649, \\\"end\\\": \\\"2025-12-03T11:59:28Z\\\", \\\"field\\\": \\\"incident_state\\\", \\\"incidentid\\\": \\\"INC10468619\\\", \\\"name\\\": \\\"Create to Resolve Duration\\\", \\\"definition\\\": \\\"MTRC00002\\\", \\\"id\\\": \\\"815d495693a9b214fce8b3f17cba106d\\\", \\\"start\\\": \\\"2025-12-03T11:48:39Z\\\", \\\"type\\\": \\\"Script calculation\\\"}, {\\\"href\\\": \\\"https://pnp-api-oss.cloud.ibm.com/v2/incidents/INC10468619/metrics/4a2dc91a47293ad0b3f39cba216d43a7\\\", \\\"active\\\": true, \\\"created\\\": \\\"2025-12-03T11:58:45Z\\\", \\\"description\\\": \\\"This metric captures the duration of time an incident is assigned to a user for each user assigned during an incident's life-cycle.\\\", \\\"field\\\": \\\"assigned_to\\\", \\\"incidentid\\\": \\\"INC10468619\\\", \\\"name\\\": \\\"Assigned to Duration\\\", \\\"definition\\\": \\\"MTRC0000003\\\", \\\"id\\\": \\\"4a2dc91a47293ad0b3f39cba216d43a7\\\", \\\"start\\\": \\\"2025-12-03T11:58:44Z\\\", \\\"type\\\": \\\"Field value duration\\\", \\\"value\\\": \\\"ANDRE AUGUSTO GONZAGA\\\"}, {\\\"href\\\": \\\"https://pnp-api-oss.cloud.ibm.com/v2/incidents/INC10468619/metrics/edab855647e536d0e6654e9b116d43c5\\\", \\\"active\\\": true, \\\"calc_complete\\\": true, \\\"created\\\": \\\"2025-12-03T11:52:10Z\\\", \\\"description\\\": \\\"This metric captures the duration of time an incident is assigned to a user for each user assigned during an incident's life-cycle.\\\", \\\"duration\\\": 397, \\\"end\\\": \\\"2025-12-03T11:58:44Z\\\", \\\"field\\\": \\\"assigned_to\\\", \\\"incidentid\\\": \\\"INC10468619\\\", \\\"name\\\": \\\"Assigned to Duration\\\", \\\"definition\\\": \\\"MTRC0000003\\\", \\\"id\\\": \\\"edab855647e536d0e6654e9b116d43c5\\\", \\\"start\\\": \\\"2025-12-03T11:52:07Z\\\", \\\"type\\\": \\\"Field value duration\\\", \\\"value\\\": \\\"Ipops-automation\\\"}, {\\\"href\\\": \\\"https://pnp-api-oss.cloud.ibm.com/v2/incidents/INC10468619/metrics/095d495693a9b214fce8b3f17cba106d\\\", \\\"active\\\": true, \\\"created\\\": \\\"2025-12-03T11:59:30Z\\\", \\\"description\\\": \\\"This metric captures the duration of time an incident has a particular state value for all state values applied during an incident's life-cycle.\\\", \\\"field\\\": \\\"incident_state\\\", \\\"incidentid\\\": \\\"INC10468619\\\", \\\"name\\\": \\\"Incident State Duration\\\", \\\"definition\\\": \\\"MTRC0000004\\\", \\\"id\\\": \\\"095d495693a9b214fce8b3f17cba106d\\\", \\\"start\\\": \\\"2025-12-03T11:59:28Z\\\", \\\"type\\\": \\\"Field value duration\\\", \\\"value\\\": \\\"Resolved\\\"}, {\\\"href\\\": \\\"https://pnp-api-oss.cloud.ibm.com/v2/incidents/INC10468619/metrics/16da499e47a536d0e6654e9b116d4353\\\", \\\"active\\\": true, \\\"calc_complete\\\": true, \\\"created\\\": \\\"2025-12-03T11:48:40Z\\\", \\\"description\\\": \\\"This metric captures the duration of time an incident has a particular state value for all state values applied during an incident's life-cycle.\\\", \\\"duration\\\": 208, \\\"end\\\": \\\"2025-12-03T11:52:07Z\\\", \\\"field\\\": \\\"incident_state\\\", \\\"incidentid\\\": \\\"INC10468619\\\", \\\"name\\\": \\\"Incident State Duration\\\", \\\"definition\\\": \\\"MTRC0000004\\\", \\\"id\\\": \\\"16da499e47a536d0e6654e9b116d4353\\\", \\\"start\\\": \\\"2025-12-03T11:48:39Z\\\", \\\"type\\\": \\\"Field value duration\\\", \\\"value\\\": \\\"New\\\"}, {\\\"href\\\": \\\"https://pnp-api-oss.cloud.ibm.com/v2/incidents/INC10468619/metrics/2dab855647e536d0e6654e9b116d43c6\\\", \\\"active\\\": true, \\\"calc_complete\\\": true, \\\"created\\\": \\\"2025-12-03T11:52:10Z\\\", \\\"description\\\": \\\"This metric captures the duration of time an incident has a particular state value for all state values applied during an incident's life-cycle.\\\", \\\"duration\\\": 441, \\\"end\\\": \\\"2025-12-03T11:59:28Z\\\", \\\"field\\\": \\\"incident_state\\\", \\\"incidentid\\\": \\\"INC10468619\\\", \\\"name\\\": \\\"Incident State Duration\\\", \\\"definition\\\": \\\"MTRC0000004\\\", \\\"id\\\": \\\"2dab855647e536d0e6654e9b116d43c6\\\", \\\"start\\\": \\\"2025-12-03T11:52:07Z\\\", \\\"type\\\": \\\"Field value duration\\\", \\\"value\\\": \\\"In Progress\\\"}, {\\\"href\\\": \\\"https://pnp-api-oss.cloud.ibm.com/v2/incidents/INC10468619/metrics/5eda499e47a536d0e6654e9b116d4353\\\", \\\"active\\\": true, \\\"calc_complete\\\": true, \\\"created\\\": \\\"2025-12-03T11:48:40Z\\\", \\\"description\\\": \\\"Overly simplified definition of first call resolution.  \\\\r\\\\n\\\\r\\\\nIf the incident is inactive and the update count (sys_mod_count) is zero, create one of these.\\\", \\\"incidentid\\\": \\\"INC10468619\\\", \\\"name\\\": \\\"First Call Resolution\\\", \\\"definition\\\": \\\"MTRC00005\\\", \\\"id\\\": \\\"5eda499e47a536d0e6654e9b116d4353\\\", \\\"type\\\": \\\"Script calculation\\\", \\\"value\\\": \\\"false\\\"}, {\\\"href\\\": \\\"https://pnp-api-oss.cloud.ibm.com/v2/incidents/INC10468619/metrics/56da499e47a536d0e6654e9b116d4354\\\", \\\"active\\\": true, \\\"created\\\": \\\"2025-12-03T11:48:40Z\\\", \\\"description\\\": \\\"This metric captures the duration of time an incident is assigned to an assignment group for each group assigned during an incident's life-cycle.\\\", \\\"field\\\": \\\"assignment_group\\\", \\\"incidentid\\\": \\\"INC10468619\\\", \\\"name\\\": \\\"Assignment Group\\\", \\\"definition\\\": \\\"MTRC00006\\\", \\\"id\\\": \\\"56da499e47a536d0e6654e9b116d4354\\\", \\\"start\\\": \\\"2025-12-03T11:48:39Z\\\", \\\"type\\\": \\\"Field value duration\\\", \\\"value\\\": \\\"is-ng-vpc\\\"}, {\\\"href\\\": \\\"https://pnp-api-oss.cloud.ibm.com/v2/incidents/INC10468619/metrics/52da499e47a536d0e6654e9b116d4346\\\", \\\"active\\\": true, \\\"created\\\": \\\"2025-12-03T11:48:40Z\\\", \\\"description\\\": \\\"Special case that closes out (ends) other metrics when an the active flag in the incident turns false\\\", \\\"field\\\": \\\"active\\\", \\\"incidentid\\\": \\\"INC10468619\\\", \\\"name\\\": \\\"Open\\\", \\\"definition\\\": \\\"MTRC0000007\\\", \\\"id\\\": \\\"52da499e47a536d0e6654e9b116d4346\\\", \\\"start\\\": \\\"2025-12-03T11:48:39Z\\\", \\\"type\\\": \\\"Field value duration\\\", \\\"value\\\": \\\"true\\\"}, {\\\"href\\\": \\\"https://pnp-api-oss.cloud.ibm.com/v2/incidents/INC10468619/metrics/deda499e47a536d0e6654e9b116d4354\\\", \\\"active\\\": true, \\\"created\\\": \\\"2025-12-03T11:48:40Z\\\", \\\"description\\\": \\\"This metric captures the time between when the Incident is created and the first time the incident status is Potential CIE.\\\", \\\"field\\\": \\\"u_status\\\", \\\"incidentid\\\": \\\"INC10468619\\\", \\\"name\\\": \\\"Create to Potential CIE\\\", \\\"definition\\\": \\\"MTRC0010003\\\", \\\"id\\\": \\\"deda499e47a536d0e6654e9b116d4354\\\", \\\"start\\\": \\\"2025-12-03T11:48:39Z\\\", \\\"type\\\": \\\"Field value duration\\\", \\\"value\\\": \\\"Normal\\\"}, {\\\"href\\\": \\\"https://pnp-api-oss.cloud.ibm.com/v2/incidents/INC10468619/metrics/1ada499e47a536d0e6654e9b116d4355\\\", \\\"active\\\": true, \\\"calc_complete\\\": true, \\\"created\\\": \\\"2025-12-03T11:48:40Z\\\", \\\"description\\\": \\\"Records the value and duration of the Incident Status field.  \\\", \\\"duration\\\": 649, \\\"end\\\": \\\"2025-12-03T11:59:28Z\\\", \\\"field\\\": \\\"u_status\\\", \\\"incidentid\\\": \\\"INC10468619\\\", \\\"name\\\": \\\"Incident status changed\\\", \\\"definition\\\": \\\"MTRC0010016\\\", \\\"id\\\": \\\"1ada499e47a536d0e6654e9b116d4355\\\", \\\"start\\\": \\\"2025-12-03T11:48:39Z\\\", \\\"type\\\": \\\"Field value duration\\\", \\\"value\\\": \\\"Normal\\\"}, {\\\"href\\\": \\\"https://pnp-api-oss.cloud.ibm.com/v2/incidents/INC10468619/metrics/52da499e47a536d0e6654e9b116d4356\\\", \\\"active\\\": true, \\\"created\\\": \\\"2025-12-03T11:48:40Z\\\", \\\"description\\\": \\\"This metric captures the time between when the Incident is created and the first time the incident status is Confirmed CIE.\\\", \\\"field\\\": \\\"u_status\\\", \\\"incidentid\\\": \\\"INC10468619\\\", \\\"name\\\": \\\"Create to Confirmed CIE\\\", \\\"definition\\\": \\\"MTRC0010004\\\", \\\"id\\\": \\\"52da499e47a536d0e6654e9b116d4356\\\", \\\"start\\\": \\\"2025-12-03T11:48:39Z\\\", \\\"type\\\": \\\"Field value duration\\\", \\\"value\\\": \\\"Normal\\\"}, {\\\"href\\\": \\\"https://pnp-api-oss.cloud.ibm.com/v2/incidents/INC10468619/metrics/607d899693a9b214fce8b3f17cba1020\\\", \\\"active\\\": true, \\\"calc_complete\\\": true, \\\"created\\\": \\\"2025-12-03T12:00:01Z\\\", \\\"description\\\": \\\"How to calculate:\\\\r\\\\nSum of all Durations of Incident status changed w/Value=Confirmed CIE existing metric\\\\r\\\\n\\\\r\\\\nDescription:\\\\r\\\\nSearches for the last time the incident was resolved. Excludes any Incident status changed that were made after resolution. Looks at the cCIE flag has been set to True.\\\", \\\"incidentid\\\": \\\"INC10468619\\\", \\\"name\\\": \\\"Time-in-cCIE\\\", \\\"definition\\\": \\\"MTRC0010016\\\", \\\"id\\\": \\\"607d899693a9b214fce8b3f17cba1020\\\", \\\"type\\\": \\\"Script calculation\\\", \\\"value\\\": \\\"0\\\"}, {\\\"href\\\": \\\"https://pnp-api-oss.cloud.ibm.com/v2/incidents/INC10468619/metrics/dc7d419e936576143ebeb91e1dba10ab\\\", \\\"active\\\": true, \\\"calc_complete\\\": true, \\\"created\\\": \\\"2025-12-03T12:00:00Z\\\", \\\"description\\\": \\\"How to calculate:\\\\r\\\\nIncident Resolved \\\\u2013 Outage End\\\\r\\\\n\\\\r\\\\nDescription:\\\\r\\\\nIncident Resolved; last time the incident was resolved. Using the start time from the metric \\\\\\\"Incident State Duration\\\\\\\" when the value is Resolved. \\\", \\\"incidentid\\\": \\\"INC10468619\\\", \\\"name\\\": \\\"Time-to-Incident-Resolved\\\", \\\"definition\\\": \\\"MTRC0010017\\\", \\\"id\\\": \\\"dc7d419e936576143ebeb91e1dba10ab\\\", \\\"type\\\": \\\"Script calculation\\\", \\\"value\\\": \\\"0\\\"}, {\\\"href\\\": \\\"https://pnp-api-oss.cloud.ibm.com/v2/incidents/INC10468619/metrics/9ada499e47a536d0e6654e9b116d4356\\\", \\\"active\\\": true, \\\"calc_complete\\\": true, \\\"created\\\": \\\"2025-12-03T11:48:40Z\\\", \\\"description\\\": \\\"Records the value and duration of the Severity(priority) field.  \\\", \\\"duration\\\": 649, \\\"end\\\": \\\"2025-12-03T11:59:28Z\\\", \\\"field\\\": \\\"priority\\\", \\\"incidentid\\\": \\\"INC10468619\\\", \\\"name\\\": \\\"Severity (Priority) Changed\\\", \\\"definition\\\": \\\"MTRC0010011\\\", \\\"id\\\": \\\"9ada499e47a536d0e6654e9b116d4356\\\", \\\"start\\\": \\\"2025-12-03T11:48:39Z\\\", \\\"type\\\": \\\"Field value duration\\\", \\\"value\\\": \\\"Sev - 3\\\"}, {\\\"href\\\": \\\"https://pnp-api-oss.cloud.ibm.com/v2/incidents/INC10468619/metrics/147dcd5e936576143ebeb91e1dba1065\\\", \\\"active\\\": true, \\\"calc_complete\\\": true, \\\"created\\\": \\\"2025-12-03T12:00:00Z\\\", \\\"description\\\": \\\"How to calculate:\\\\r\\\\nSum of all Durations of Incident status changed w/Value=Potential CIE existing metric\\\\r\\\\n\\\\r\\\\nDescription:\\\\r\\\\nSearches for the last time the incident was resolved. Excludes any Incident status changed that were made after resolution.  Looks at the pCIE flag has been set to True.\\\", \\\"incidentid\\\": \\\"INC10468619\\\", \\\"name\\\": \\\"Time-in-pCIE\\\", \\\"definition\\\": \\\"MTRC0010014\\\", \\\"id\\\": \\\"147dcd5e936576143ebeb91e1dba1065\\\", \\\"type\\\": \\\"Script calculation\\\", \\\"value\\\": \\\"0\\\"}]\"",
  "metadata": {
    "zones": [
      {
        "qz": "qz1",
        "zone": "eu-es-3",
        "mzone": "mzone2y7",
        "region": "eu-es",
        "datacenter": "mad05",
        "dc_hostname": "mad3",
        "sds_zonal_cluster": [
          "py1"
        ],
        "sds_regional_cluster": "cw1",
        "vsi_based_resource_id_prefix": "02y7",
        "extid_based_resource_id_prefix": "r050"
      }
    ],
    "hostnames": [
      "mad3-qz1-sr1-rk054-s48",
      "mad3-qz1-sr1-rk060-s06"
    ]
  }
}